MANIFEST.in
README.md
README.rst
setup.py
pyTweetBot/__init__.py
pyTweetBot/__main__.py
pyTweetBot/convert_dataset.py
pyTweetBot/create_database.py
pyTweetBot/direct_messages.py
pyTweetBot/execute_actions.py
pyTweetBot/export_database.py
pyTweetBot/find_follows.py
pyTweetBot/find_github_tweets.py
pyTweetBot/find_retweets.py
pyTweetBot/find_tweets.py
pyTweetBot/find_unfollows.py
pyTweetBot/follower_dataset.py
pyTweetBot/import_database.py
pyTweetBot/list_actions.py
pyTweetBot/model_testing.py
pyTweetBot/model_training.py
pyTweetBot/retweet_dataset.py
pyTweetBot/statistics_generator.py
pyTweetBot/tweet_dataset.py
pyTweetBot/tweet_training.py
pyTweetBot/unfollow_dataset.py
pyTweetBot/update_statistics.py
pyTweetBot.egg-info/PKG-INFO
pyTweetBot.egg-info/SOURCES.txt
pyTweetBot.egg-info/dependency_links.txt
pyTweetBot.egg-info/requires.txt
pyTweetBot.egg-info/top_level.txt
pyTweetBot/config/BotConfig.py
pyTweetBot/config/__init__.py
pyTweetBot/config/default_config.py
pyTweetBot/config/required_fields.py
pyTweetBot/db/DBConnector.py
pyTweetBot/db/__init__.py
pyTweetBot/db/obj/Action.py
pyTweetBot/db/obj/Base.py
pyTweetBot/db/obj/Follower.py
pyTweetBot/db/obj/Following.py
pyTweetBot/db/obj/Friend.py
pyTweetBot/db/obj/ImpactStatistics.py
pyTweetBot/db/obj/Model.py
pyTweetBot/db/obj/ModelTokens.py
pyTweetBot/db/obj/Statistic.py
pyTweetBot/db/obj/Tweeted.py
pyTweetBot/db/obj/__init__.py
pyTweetBot/directmessages/__init__.py
pyTweetBot/directmessages/directmessages.py
pyTweetBot/directmessages/pyTweetBotDirectMessageAction.py
pyTweetBot/directmessages/pyTweetBotDirectMessager.py
pyTweetBot/executor/ActionScheduler.py
pyTweetBot/executor/ExecutorThread.py
pyTweetBot/executor/__init__.py
pyTweetBot/friends/FriendsManager.py
pyTweetBot/friends/__init__.py
pyTweetBot/learning/CensorModel.py
pyTweetBot/learning/Classifier.py
pyTweetBot/learning/Dataset.py
pyTweetBot/learning/DecisionTree.py
pyTweetBot/learning/Model.py
pyTweetBot/learning/NaiveBayesClassifier.py
pyTweetBot/learning/__init__.py
pyTweetBot/learning/features/BagOf2Grams.py
pyTweetBot/learning/features/BagOf3Grams.py
pyTweetBot/learning/features/BagOfGrams.py
