Metadata-Version: 1.1
Name: pyTweetBot
Version: 0.1
Summary: A Twitter bot to collect articles and news from the Web and tweet/retweet it on your feed
Home-page: https://github.com/nschaetti/pyTweetBot
Author: Nils Schaetti
Author-email: n.schaetti@gmail.com
License: GPL
Keywords: twitter bot nlp news tweet
Platform: UNKNOWN
Classifier: Development Status :: 3 - Alpha
Classifier: License :: OSI Approved :: GNU General Public License v3 (GPLv3)
Classifier: Topic :: Internet :: WWW/HTTP :: Dynamic Content :: News/Diary
